biobb_pmx/__init__.py
biobb_pmx/py.typed
biobb_pmx/pmxbiobb/__init__.py
biobb_pmx/pmxbiobb/common.py
biobb_pmx/pmxbiobb/pmxanalyse.py
biobb_pmx/pmxbiobb/pmxatom_mapping.py
biobb_pmx/pmxbiobb/pmxcreate_top.py
biobb_pmx/pmxbiobb/pmxgentop.py
biobb_pmx/pmxbiobb/pmxligand_hybrid.py
biobb_pmx/pmxbiobb/pmxmerge_ff.py
biobb_pmx/pmxbiobb/pmxmutate.py
biobb_pmx/test/__init__.py
biobb_pmx-5.2.1.dist-info/licenses/LICENSE
biobb_pmx-5.2.1.dist-info/METADATA
biobb_pmx-5.2.1.dist-info/WHEEL
biobb_pmx-5.2.1.dist-info/entry_points.txt
biobb_pmx-5.2.1.dist-info/top_level.txt
biobb_pmx-5.2.1.dist-info/RECORD
