Metadata-Version: 2.4
Name: biobb_pmx
Version: 5.2.1
Summary: Biobb_pmx is the Biobb module collection to perform PMX (http://pmx.mpibpc.mpg.de) executions.
Home-page: https://github.com/bioexcel/biobb_pmx
Author: Biobb developers
Author-email: pau.andrio@bsc.es
Project-URL: Documentation, http://biobb-pmx.readthedocs.io/en/latest/
Project-URL: Bioexcel, https://bioexcel.eu/
Keywords: Bioinformatics Workflows BioExcel Compatibility
Classifier: Development Status :: 5 - Production/Stable
Classifier: Programming Language :: Python :: 3.10
Classifier: Programming Language :: Python :: 3.11
Classifier: Programming Language :: Python :: 3.12
Classifier: License :: OSI Approved :: Apache Software License
Classifier: Operating System :: MacOS :: MacOS X
Classifier: Operating System :: POSIX
Classifier: Operating System :: Unix
Requires-Python: >=3.10
License-File: LICENSE
Requires-Dist: biobb_common==5.2.1
Dynamic: author
Dynamic: author-email
Dynamic: classifier
Dynamic: description
Dynamic: description-content-type
Dynamic: home-page
Dynamic: keywords
Dynamic: license-file
Dynamic: project-url
Dynamic: requires-dist
Dynamic: requires-python
Dynamic: summary
